Workbook
Name ServiceList: Services!$B$6:$B$40
Name ServiceTable: Services!$B$6:$E$40

Sheet Invoice
B3: =Setup!C4 | E3: INVOICE
B4: =Setup!C5
B5: =Setup!C6 | E5: Invoice No. | G5: INV-0001
B6: =Setup!C7 | E6: Date
B7: =Setup!C8&" | "&Setup!C9 | E7: Due Date | G7: =IF(G6="","",G6+Setup!C13)
B8: =Setup!C10 | E8: Balance Due | G8: =G40
B11: BILL TO | D11: SERVICE LOCATION
B12: [Client Name] | D12: [Job site or project name]
B13: [Company] | D13: [Street Address]
B14: [Street Address] | D14: [City, State ZIP]
B15: [City, State ZIP]
B16: [Email / Phone]
B18: ITEM | C18: DESCRIPTION | D18: QTY | E18: UNIT | F18: RATE | G18: AMOUNT
C19: =IF(B19="","",IFERROR(VLOOKUP(B19,Services!$B$6:$E$40,2,FALSE)&"","")) | E19: =IF(B19="","",IFERROR(VLOOKUP(B19,Services!$B$6:$E$40,3,FALSE)&"","")) | F19: =IF(B19="","",IFERROR(IF(VLOOKUP(B19,Services!$B$6:$E$40,4,FALSE)="","",VLOOKUP(B19,Services!$B$6:$E$40,4,FALSE)),"")) | G19: =IF(OR(D19="",F19=""),"",D19*F19)
C20: =IF(B20="","",IFERROR(VLOOKUP(B20,Services!$B$6:$E$40,2,FALSE)&"","")) | E20: =IF(B20="","",IFERROR(VLOOKUP(B20,Services!$B$6:$E$40,3,FALSE)&"","")) | F20: =IF(B20="","",IFERROR(IF(VLOOKUP(B20,Services!$B$6:$E$40,4,FALSE)="","",VLOOKUP(B20,Services!$B$6:$E$40,4,FALSE)),"")) | G20: =IF(OR(D20="",F20=""),"",D20*F20)
C21: =IF(B21="","",IFERROR(VLOOKUP(B21,Services!$B$6:$E$40,2,FALSE)&"","")) | E21: =IF(B21="","",IFERROR(VLOOKUP(B21,Services!$B$6:$E$40,3,FALSE)&"","")) | F21: =IF(B21="","",IFERROR(IF(VLOOKUP(B21,Services!$B$6:$E$40,4,FALSE)="","",VLOOKUP(B21,Services!$B$6:$E$40,4,FALSE)),"")) | G21: =IF(OR(D21="",F21=""),"",D21*F21)
C22: =IF(B22="","",IFERROR(VLOOKUP(B22,Services!$B$6:$E$40,2,FALSE)&"","")) | E22: =IF(B22="","",IFERROR(VLOOKUP(B22,Services!$B$6:$E$40,3,FALSE)&"","")) | F22: =IF(B22="","",IFERROR(IF(VLOOKUP(B22,Services!$B$6:$E$40,4,FALSE)="","",VLOOKUP(B22,Services!$B$6:$E$40,4,FALSE)),"")) | G22: =IF(OR(D22="",F22=""),"",D22*F22)
C23: =IF(B23="","",IFERROR(VLOOKUP(B23,Services!$B$6:$E$40,2,FALSE)&"","")) | E23: =IF(B23="","",IFERROR(VLOOKUP(B23,Services!$B$6:$E$40,3,FALSE)&"","")) | F23: =IF(B23="","",IFERROR(IF(VLOOKUP(B23,Services!$B$6:$E$40,4,FALSE)="","",VLOOKUP(B23,Services!$B$6:$E$40,4,FALSE)),"")) | G23: =IF(OR(D23="",F23=""),"",D23*F23)
C24: =IF(B24="","",IFERROR(VLOOKUP(B24,Services!$B$6:$E$40,2,FALSE)&"","")) | E24: =IF(B24="","",IFERROR(VLOOKUP(B24,Services!$B$6:$E$40,3,FALSE)&"","")) | F24: =IF(B24="","",IFERROR(IF(VLOOKUP(B24,Services!$B$6:$E$40,4,FALSE)="","",VLOOKUP(B24,Services!$B$6:$E$40,4,FALSE)),"")) | G24: =IF(OR(D24="",F24=""),"",D24*F24)
C25: =IF(B25="","",IFERROR(VLOOKUP(B25,Services!$B$6:$E$40,2,FALSE)&"","")) | E25: =IF(B25="","",IFERROR(VLOOKUP(B25,Services!$B$6:$E$40,3,FALSE)&"","")) | F25: =IF(B25="","",IFERROR(IF(VLOOKUP(B25,Services!$B$6:$E$40,4,FALSE)="","",VLOOKUP(B25,Services!$B$6:$E$40,4,FALSE)),"")) | G25: =IF(OR(D25="",F25=""),"",D25*F25)
C26: =IF(B26="","",IFERROR(VLOOKUP(B26,Services!$B$6:$E$40,2,FALSE)&"","")) | E26: =IF(B26="","",IFERROR(VLOOKUP(B26,Services!$B$6:$E$40,3,FALSE)&"","")) | F26: =IF(B26="","",IFERROR(IF(VLOOKUP(B26,Services!$B$6:$E$40,4,FALSE)="","",VLOOKUP(B26,Services!$B$6:$E$40,4,FALSE)),"")) | G26: =IF(OR(D26="",F26=""),"",D26*F26)
C27: =IF(B27="","",IFERROR(VLOOKUP(B27,Services!$B$6:$E$40,2,FALSE)&"","")) | E27: =IF(B27="","",IFERROR(VLOOKUP(B27,Services!$B$6:$E$40,3,FALSE)&"","")) | F27: =IF(B27="","",IFERROR(IF(VLOOKUP(B27,Services!$B$6:$E$40,4,FALSE)="","",VLOOKUP(B27,Services!$B$6:$E$40,4,FALSE)),"")) | G27: =IF(OR(D27="",F27=""),"",D27*F27)
C28: =IF(B28="","",IFERROR(VLOOKUP(B28,Services!$B$6:$E$40,2,FALSE)&"","")) | E28: =IF(B28="","",IFERROR(VLOOKUP(B28,Services!$B$6:$E$40,3,FALSE)&"","")) | F28: =IF(B28="","",IFERROR(IF(VLOOKUP(B28,Services!$B$6:$E$40,4,FALSE)="","",VLOOKUP(B28,Services!$B$6:$E$40,4,FALSE)),"")) | G28: =IF(OR(D28="",F28=""),"",D28*F28)
C29: =IF(B29="","",IFERROR(VLOOKUP(B29,Services!$B$6:$E$40,2,FALSE)&"","")) | E29: =IF(B29="","",IFERROR(VLOOKUP(B29,Services!$B$6:$E$40,3,FALSE)&"","")) | F29: =IF(B29="","",IFERROR(IF(VLOOKUP(B29,Services!$B$6:$E$40,4,FALSE)="","",VLOOKUP(B29,Services!$B$6:$E$40,4,FALSE)),"")) | G29: =IF(OR(D29="",F29=""),"",D29*F29)
C30: =IF(B30="","",IFERROR(VLOOKUP(B30,Services!$B$6:$E$40,2,FALSE)&"","")) | E30: =IF(B30="","",IFERROR(VLOOKUP(B30,Services!$B$6:$E$40,3,FALSE)&"","")) | F30: =IF(B30="","",IFERROR(IF(VLOOKUP(B30,Services!$B$6:$E$40,4,FALSE)="","",VLOOKUP(B30,Services!$B$6:$E$40,4,FALSE)),"")) | G30: =IF(OR(D30="",F30=""),"",D30*F30)
... C33: =IF(B33="","",IFERROR(VLOOKUP(B33,Services!$B$6:$E$40,2,FALSE)&"","")) | E33: =IF(B33="","",IFERROR(VLOOKUP(B33,Services!$B$6:$E$40,3,FALSE)&"","")) | F33: =IF(B33="","",IFERROR(IF(VLOOKUP(B33,Services!$B$6:$E$40,4,FALSE)="","",VLOOKUP(B33,Services!$B$6:$E$40,4,FALSE)),"")) | G33: =IF(OR(D33="",F33=""),"",D33*F33)
B35: PAYMENT DETAILS | E35: Subtotal | G35: =SUM(G19:G33)
B36: =Setup!C14 | E36: Discount | G36: 0
E37: ="Tax ("&TEXT(Setup!C12,"0.0#%")&")" | G37: =ROUND((G35-G36)*Setup!C12,2)
E38: Total | G38: =G35-G36+G37
E39: Amount Paid | G39: 0
E40: BALANCE DUE | G40: =G38-G39
B43: =Setup!C15
B44: ="Questions? "&Setup!C8&" | "&Setup!C9

Sheet Estimate
B3: =Setup!C4 | E3: ESTIMATE
B4: =Setup!C5
B5: =Setup!C6 | E5: Estimate No. | G5: EST-0001
B6: =Setup!C7 | E6: Date
B7: =Setup!C8&" | "&Setup!C9 | E7: Valid Until | G7: =IF(G6="","",G6+Setup!C16)
B8: =Setup!C10 | E8: Estimate Total | G8: =G39
B11: BILL TO | D11: PROJECT / LOCATION
B12: [Client Name] | D12: [Job site or project name]
B13: [Company] | D13: [Street Address]
B14: [Street Address] | D14: [City, State ZIP]
B15: [City, State ZIP]
B16: [Email / Phone]
B18: ITEM | C18: DESCRIPTION | D18: QTY | E18: UNIT | F18: RATE | G18: AMOUNT
C19: =IF(B19="","",IFERROR(VLOOKUP(B19,Services!$B$6:$E$40,2,FALSE)&"","")) | E19: =IF(B19="","",IFERROR(VLOOKUP(B19,Services!$B$6:$E$40,3,FALSE)&"","")) | F19: =IF(B19="","",IFERROR(IF(VLOOKUP(B19,Services!$B$6:$E$40,4,FALSE)="","",VLOOKUP(B19,Services!$B$6:$E$40,4,FALSE)),"")) | G19: =IF(OR(D19="",F19=""),"",D19*F19)
C20: =IF(B20="","",IFERROR(VLOOKUP(B20,Services!$B$6:$E$40,2,FALSE)&"","")) | E20: =IF(B20="","",IFERROR(VLOOKUP(B20,Services!$B$6:$E$40,3,FALSE)&"","")) | F20: =IF(B20="","",IFERROR(IF(VLOOKUP(B20,Services!$B$6:$E$40,4,FALSE)="","",VLOOKUP(B20,Services!$B$6:$E$40,4,FALSE)),"")) | G20: =IF(OR(D20="",F20=""),"",D20*F20)
C21: =IF(B21="","",IFERROR(VLOOKUP(B21,Services!$B$6:$E$40,2,FALSE)&"","")) | E21: =IF(B21="","",IFERROR(VLOOKUP(B21,Services!$B$6:$E$40,3,FALSE)&"","")) | F21: =IF(B21="","",IFERROR(IF(VLOOKUP(B21,Services!$B$6:$E$40,4,FALSE)="","",VLOOKUP(B21,Services!$B$6:$E$40,4,FALSE)),"")) | G21: =IF(OR(D21="",F21=""),"",D21*F21)
C22: =IF(B22="","",IFERROR(VLOOKUP(B22,Services!$B$6:$E$40,2,FALSE)&"","")) | E22: =IF(B22="","",IFERROR(VLOOKUP(B22,Services!$B$6:$E$40,3,FALSE)&"","")) | F22: =IF(B22="","",IFERROR(IF(VLOOKUP(B22,Services!$B$6:$E$40,4,FALSE)="","",VLOOKUP(B22,Services!$B$6:$E$40,4,FALSE)),"")) | G22: =IF(OR(D22="",F22=""),"",D22*F22)
C23: =IF(B23="","",IFERROR(VLOOKUP(B23,Services!$B$6:$E$40,2,FALSE)&"","")) | E23: =IF(B23="","",IFERROR(VLOOKUP(B23,Services!$B$6:$E$40,3,FALSE)&"","")) | F23: =IF(B23="","",IFERROR(IF(VLOOKUP(B23,Services!$B$6:$E$40,4,FALSE)="","",VLOOKUP(B23,Services!$B$6:$E$40,4,FALSE)),"")) | G23: =IF(OR(D23="",F23=""),"",D23*F23)
C24: =IF(B24="","",IFERROR(VLOOKUP(B24,Services!$B$6:$E$40,2,FALSE)&"","")) | E24: =IF(B24="","",IFERROR(VLOOKUP(B24,Services!$B$6:$E$40,3,FALSE)&"","")) | F24: =IF(B24="","",IFERROR(IF(VLOOKUP(B24,Services!$B$6:$E$40,4,FALSE)="","",VLOOKUP(B24,Services!$B$6:$E$40,4,FALSE)),"")) | G24: =IF(OR(D24="",F24=""),"",D24*F24)
C25: =IF(B25="","",IFERROR(VLOOKUP(B25,Services!$B$6:$E$40,2,FALSE)&"","")) | E25: =IF(B25="","",IFERROR(VLOOKUP(B25,Services!$B$6:$E$40,3,FALSE)&"","")) | F25: =IF(B25="","",IFERROR(IF(VLOOKUP(B25,Services!$B$6:$E$40,4,FALSE)="","",VLOOKUP(B25,Services!$B$6:$E$40,4,FALSE)),"")) | G25: =IF(OR(D25="",F25=""),"",D25*F25)
C26: =IF(B26="","",IFERROR(VLOOKUP(B26,Services!$B$6:$E$40,2,FALSE)&"","")) | E26: =IF(B26="","",IFERROR(VLOOKUP(B26,Services!$B$6:$E$40,3,FALSE)&"","")) | F26: =IF(B26="","",IFERROR(IF(VLOOKUP(B26,Services!$B$6:$E$40,4,FALSE)="","",VLOOKUP(B26,Services!$B$6:$E$40,4,FALSE)),"")) | G26: =IF(OR(D26="",F26=""),"",D26*F26)
C27: =IF(B27="","",IFERROR(VLOOKUP(B27,Services!$B$6:$E$40,2,FALSE)&"","")) | E27: =IF(B27="","",IFERROR(VLOOKUP(B27,Services!$B$6:$E$40,3,FALSE)&"","")) | F27: =IF(B27="","",IFERROR(IF(VLOOKUP(B27,Services!$B$6:$E$40,4,FALSE)="","",VLOOKUP(B27,Services!$B$6:$E$40,4,FALSE)),"")) | G27: =IF(OR(D27="",F27=""),"",D27*F27)
C28: =IF(B28="","",IFERROR(VLOOKUP(B28,Services!$B$6:$E$40,2,FALSE)&"","")) | E28: =IF(B28="","",IFERROR(VLOOKUP(B28,Services!$B$6:$E$40,3,FALSE)&"","")) | F28: =IF(B28="","",IFERROR(IF(VLOOKUP(B28,Services!$B$6:$E$40,4,FALSE)="","",VLOOKUP(B28,Services!$B$6:$E$40,4,FALSE)),"")) | G28: =IF(OR(D28="",F28=""),"",D28*F28)
C29: =IF(B29="","",IFERROR(VLOOKUP(B29,Services!$B$6:$E$40,2,FALSE)&"","")) | E29: =IF(B29="","",IFERROR(VLOOKUP(B29,Services!$B$6:$E$40,3,FALSE)&"","")) | F29: =IF(B29="","",IFERROR(IF(VLOOKUP(B29,Services!$B$6:$E$40,4,FALSE)="","",VLOOKUP(B29,Services!$B$6:$E$40,4,FALSE)),"")) | G29: =IF(OR(D29="",F29=""),"",D29*F29)
C30: =IF(B30="","",IFERROR(VLOOKUP(B30,Services!$B$6:$E$40,2,FALSE)&"","")) | E30: =IF(B30="","",IFERROR(VLOOKUP(B30,Services!$B$6:$E$40,3,FALSE)&"","")) | F30: =IF(B30="","",IFERROR(IF(VLOOKUP(B30,Services!$B$6:$E$40,4,FALSE)="","",VLOOKUP(B30,Services!$B$6:$E$40,4,FALSE)),"")) | G30: =IF(OR(D30="",F30=""),"",D30*F30)
... C33: =IF(B33="","",IFERROR(VLOOKUP(B33,Services!$B$6:$E$40,2,FALSE)&"","")) | E33: =IF(B33="","",IFERROR(VLOOKUP(B33,Services!$B$6:$E$40,3,FALSE)&"","")) | F33: =IF(B33="","",IFERROR(IF(VLOOKUP(B33,Services!$B$6:$E$40,4,FALSE)="","",VLOOKUP(B33,Services!$B$6:$E$40,4,FALSE)),"")) | G33: =IF(OR(D33="",F33=""),"",D33*F33)
B35: TERMS | E35: Subtotal | G35: =SUM(G19:G33)
B36: =Setup!C17 | E36: Discount | G36: 0
E37: ="Tax ("&TEXT(Setup!C12,"0.0#%")&")" | G37: =ROUND((G35-G36)*Setup!C12,2)
E38: Total | G38: =G35-G36+G37
E39: ESTIMATE TOTAL | G39: =G38
B42: =Setup!C15
B43: ="Questions? "&Setup!C8&" | "&Setup!C9

Sheet Services
B2: Services & Prices
B3: Fill in your prices once. Items you add here appear in the Item dropdown on the Invoice and Estimate.
B5: SERVICE | C5: DESCRIPTION (OPTIONAL) | D5: UNIT | E5: RATE
B6: Consultation | D6: each
B7: Standard service | D7: each
B8: Additional hour | D8: hour
B9: Materials | D9: each
B10: Travel / call-out fee | D10: each
B11: Rush service | D11: each

Sheet Setup
B2: Setup - enter once
B3: Everything here flows into the Invoice and Estimate automatically.
B4: Business name | C4: [Your Business Name]
B5: Tagline | C5: [Your tagline]
B6: Address line 1 | C6: [Street Address]
B7: Address line 2 | C7: [City, State ZIP]
B8: Phone | C8: [Phone]
B9: Email | C9: [Email]
B10: Website | C10: [Website]
B11: TAX & TERMS
B12: Tax rate | C12: 0
B13: Payment terms (days) | C13: 14
B14: Payment details | C14: [How to pay: bank transfer, card, check, payment link]
B15: Thank-you note | C15: Thank you for your business!
B16: Estimate valid for (days) | C16: 30
B17: Estimate terms | C17: [Estimate terms, for example a deposit to book]

Sheet How To Use
B2: How to use this template
B4: 1. Setup: enter your business details, tax rate and terms once.
B5: 2. Services: enter your prices. Add more services in the empty rows.
B6: 3. Invoice: pick each Item from the dropdown. Description, unit and rate fill in; type a quantity.
B7: For a one-off item, type it in the Item cell and type its rate.
B8: 4. Enter the invoice number, the date, the client and any discount or amount already paid.
B9: Due date, tax, total and balance due calculate automatically.
B10: 5. Estimate: works the same way, with a valid-until date and your estimate terms.
B11: 6. Print or save as PDF (File > Print, or File > Download > PDF in Google Sheets). The page is set to fit one sheet.
B12: Duplicate the Invoice tab for each new invoice, or save a copy of the file per client.
B13: Formula cells are protected so they are not overwritten by accident. To change them: Review > Unprotect Sheet (no password).
B14: Currency: select the money cells and choose your currency under Format Cells / Format > Number.
B15: Works in Microsoft Excel, Google Sheets, Apple Numbers and LibreOffice. This is a template, not tax, legal or accounting advice.

Sheet Ready-made for your trade
A1: Want this ready-made for your trade?
A2: Each kit comes with your trade's services already filled in, an estimate tab and fillable PDFs; most also include 8 matching social media posts.
A4: Business kit | B4: Price | C4: Link
A5: Car Detailing Business Kit | B5: $9.99 | C5: https://the-fixer.org/p/car-detailing-business-kit/?from=free-xlsx
A6: DJ Booking Kit | B6: $9.99 | C6: https://the-fixer.org/p/dj-booking-kit/?from=free-xlsx
A7: Dog Walking Business Kit | B7: $9.99 | C7: https://the-fixer.org/p/dog-walking-business-kit/?from=free-xlsx
A8: House Cleaning Business Kit | B8: $9.99 | C8: https://the-fixer.org/p/house-cleaning-business-kit/?from=free-xlsx
A9: Personal Trainer Business Kit | B9: $9.99 | C9: https://the-fixer.org/p/personal-trainer-business-kit/?from=free-xlsx
A10: Pet Grooming Business Kit | B10: $9.99 | C10: https://the-fixer.org/p/pet-grooming-business-kit/?from=free-xlsx
A11: Plumbing Business Kit | B11: $9.99 | C11: https://the-fixer.org/p/plumbing-business-kit/?from=free-xlsx
A13: Every template: https://the-fixer.org
